discord/__init__.py
discord_api-1.0.1.dist-info/LICENSE
discord_api-1.0.1.dist-info/METADATA
discord_api-1.0.1.dist-info/WHEEL
discord_api-1.0.1.dist-info/top_level.txt
discord_api-1.0.1.dist-info/RECORD
