Metadata-Version: 2.1
Name: discord-api
Version: 1.0.1
Summary: A clone of discord.py
Home-page: UNKNOWN
License: GPL-V3
Platform: UNKNOWN
Requires-Python: >=3.6
